artha/__init__.py
artha/db.py
artha/main.py
artha/server.py
artha/settings.py
artha/tlit.py
artha/ui/index.html
artha/ui/vite.svg
artha/ui/assets/index-D8b4DHJx.css
artha/ui/assets/index-DK-xQhXp.js
artha/ui/assets/react-CHdo91hT.svg
artha/web/books.py
artha-0.1.2.dist-info/METADATA
artha-0.1.2.dist-info/WHEEL
artha-0.1.2.dist-info/entry_points.txt
artha-0.1.2.dist-info/RECORD
